Workbook

Sheet Полный список
A1: Формулировка | B1: Число запросов
A2: пленка на | B2: 112042
A3: оклейка пленкой | B3: 21001
A4: оклейка авто | B4: 13852
A5: пленка цена | B5: 11460
A6: защитная пленка на | B6: 11100
A7: пленка на телефон | B7: 9953
A8: полиуретановая пленка | B8: 9575
A9: пленка на стекло | B9: 9419
A10: оклейка авто пленкой | B10: 8682
A11: пленка на окна | B11: 7630
A12: наклеить пленку на | B12: 5619
A13: пленка на авто | B13: 5295
... A9161: заказать оклейку авто | B9161: 1
B9162: =SUM(B2:B9161)/(ROWS(A:A)-2) -> 90.474891 | C9162: =AVERAGE(B2:B9161) -> 90.474891

Sheet Семантическое ядро
A1: Формулировка | B1: Число запросов | C1: Кластер | D1: Релевантность | E1: Статус запроса (температура) | F1: Приоритет | G1: Элемент | H1: Услуга | I1: Кластер 2
A2: оклейка пленкой | B2: 21001 | C2: Оклейка плёнкой | D2: Средняя | E2: Тёплый (коммерческий, выбирает исполнителя) | F2: Высокий | G2: Общий / не указан | H2: Плёнка/Оклейка | I2: Оклейка плёнкой — Общий / не указан
A3: оклейка авто | B3: 13852 | C3: Оклейка плёнкой | D3: Средняя | E3: Горячий (коммерческий) | F3: Высокий | G3: Общий / не указан | H3: Плёнка/Оклейка | I3: Оклейка плёнкой — Общий / не указан
A4: пленка цена | B4: 11460 | C4: Плёнка | D4: Средняя | E4: Горячий (коммерческий) | F4: Высокий | G4: Общий / не указан | H4: Плёнка/Оклейка | I4: Плёнка (общий запрос) — Общий / не указан
A5: оклейка авто пленкой | B5: 8682 | C5: Оклейка плёнкой | D5: Высокая | E5: Тёплый (коммерческий, выбирает исполнителя) | F5: Высокий | G5: Общий / не указан | H5: Плёнка/Оклейка | I5: Оклейка плёнкой — Общий / не указан
A6: пленка на авто | B6: 5295 | C6: Плёнка | D6: Высокая | E6: Средний интерес (изучает тему) | F6: Высокий | G6: Общий / не указан | H6: Плёнка/Оклейка | I6: Плёнка (общий запрос) — Общий / не указан
A7: цена оклейки | B7: 4050 | C7: Оклейка плёнкой | D7: Средняя | E7: Тёплый (коммерческий, выбирает исполнителя) | F7: Средний | G7: Общий / не указан | H7: Плёнка/Оклейка | I7: Оклейка плёнкой — Общий / не указан
A8: пленка на автомобиль | B8: 3947 | C8: Плёнка | D8: Высокая | E8: Средний интерес (изучает тему) | F8: Высокий | G8: Общий / не указан | H8: Плёнка/Оклейка | I8: Плёнка (общий запрос) — Общий / не указан
A9: оклейка автомобиля | B9: 3526 | C9: Оклейка плёнкой | D9: Средняя | E9: Тёплый (коммерческий, выбирает исполнителя) | F9: Высокий | G9: Общий / не указан | H9: Плёнка/Оклейка | I9: Оклейка плёнкой — Общий / не указан
A10: оклейка пленкой москва | B10: 3001 | C10: Оклейка плёнкой | D10: Средняя | E10: Тёплый (коммерческий, выбирает исполнителя) | F10: Высокий | G10: Общий / не указан | H10: Плёнка/Оклейка | I10: Оклейка плёнкой — Общий / не указан
A11: оклейка машины | B11: 2915 | C11: Оклейка плёнкой | D11: Средняя | E11: Тёплый (коммерческий, выбирает исполнителя) | F11: Высокий | G11: Общий / не указан | H11: Плёнка/Оклейка | I11: Оклейка плёнкой — Общий / не указан
A12: оклейка пленкой цена | B12: 2772 | C12: Оклейка плёнкой | D12: Высокая | E12: Горячий (коммерческий) | F12: Высокий | G12: Общий / не указан | H12: Плёнка/Оклейка | I12: Оклейка плёнкой — Общий / не указан
A13: оклейка авто москва | B13: 2589 | C13: Оклейка плёнкой | D13: Средняя | E13: Тёплый (коммерческий, выбирает исполнителя) | F13: Высокий | G13: Общий / не указан | H13: Плёнка/Оклейка | I13: Оклейка плёнкой — Общий / не указан
... A692: полиуретановая пленка для фар автомобиля | B692: 50 | C692: Полиуретановая защитная плёнка | D692: Высокая | E692: Средний интерес (изучает тему) | F692: Низкий | G692: Фары | H692: Плёнка/Оклейка | I692: Полиуретановая защитная плёнка — Фары
B693: =SUM(B2:B692)/691 -> 332.63965
B694: =SUM(B2:B692)/ROWS(A:A) -> 331.20173 | C694: =AVERAGE(B1:B688) -> 334.2853

Sheet Сравнение
A1: Кластер | B1: Кол-во запросов | C1: Сума запросов | D1: % соотношение к всем запросам | F1: Элемент | G1: Кол-во запросов | H1: Сума запросов | I1: % соотношение к всем запросам
A2: Оклейка плёнкой | B2: =COUNTIF('Семантическое ядро'!C:C,A2) -> 193 | C2: =SUMIF('Семантическое ядро'!C:C,A2,'Семантическое ядро'!B:B) -> 99990 | D2: =C2/SUM('Семантическое ядро'!B:B) -> 0.43376252 | F2: Общий / не указан | G2: =COUNTIF('Семантическое ядро'!G:G,F2) -> 594 | H2: =SUMIF('Семантическое ядро'!G:G,F2,'Семантическое ядро'!B:B) -> 210236 | I2: =H2/SUM('Семантическое ядро'!B:B) -> 0.91201618
A3: Плёнка | B3: =COUNTIF('Семантическое ядро'!C:C,A3) -> 358 | C3: =SUMIF('Семантическое ядро'!C:C,A3,'Семантическое ядро'!B:B) -> 98645 | D3: =C3/SUM('Семантическое ядро'!B:B) -> 0.42792783 | F3: Лобовое стекло | G3: =COUNTIF('Семантическое ядро'!G:G,F3) -> 29 | H3: =SUMIF('Семантическое ядро'!G:G,F3,'Семантическое ядро'!B:B) -> 7412 | I3: =H3/SUM('Семантическое ядро'!B:B) -> 0.032153693
A4: Полиуретановая защитная плёнка | B4: =COUNTIF('Семантическое ядро'!C:C,A4) -> 37 | C4: =SUMIF('Семантическое ядро'!C:C,A4,'Семантическое ядро'!B:B) -> 10138 | D4: =C4/SUM('Семантическое ядро'!B:B) -> 0.043979242 | F4: Кузов | G4: =COUNTIF('Семантическое ядро'!G:G,F4) -> 22 | H4: =SUMIF('Семантическое ядро'!G:G,F4,'Семантическое ядро'!B:B) -> 5754 | I4: =H4/SUM('Семантическое ядро'!B:B) -> 0.024961192
A5: Антигравийная защитная плёнка | B5: =COUNTIF('Семантическое ядро'!C:C,A5) -> 29 | C5: =SUMIF('Семантическое ядро'!C:C,A5,'Семантическое ядро'!B:B) -> 7205 | D5: =C5/SUM('Семантическое ядро'!B:B) -> 0.031255715 | F5: Фары | G5: =COUNTIF('Семантическое ядро'!G:G,F5) -> 13 | H5: =SUMIF('Семантическое ядро'!G:G,F5,'Семантическое ядро'!B:B) -> 2032 | I5: =H5/SUM('Семантическое ядро'!B:B) -> 0.0088149359
A6: Защитная плёнка | B6: =COUNTIF('Семантическое ядро'!C:C,A6) -> 36 | C6: =SUMIF('Семантическое ядро'!C:C,A6,'Семантическое ядро'!B:B) -> 6666 | D6: =C6/SUM('Семантическое ядро'!B:B) -> 0.028917501 | F6: Капот | G6: =COUNTIF('Семантическое ядро'!G:G,F6) -> 6 | H6: =SUMIF('Семантическое ядро'!G:G,F6,'Семантическое ядро'!B:B) -> 1342 | I6: =H6/SUM('Семантическое ядро'!B:B) -> 0.0058216752
A7: Бронеплёнка / бронирование | B7: =COUNTIF('Семантическое ядро'!C:C,A7) -> 22 | C7: =SUMIF('Семантическое ядро'!C:C,A7,'Семантическое ядро'!B:B) -> 3813 | D7: =C7/SUM('Семантическое ядро'!B:B) -> 0.016541019 | F7: Пороги | G7: =COUNTIF('Семантическое ядро'!G:G,F7) -> 8 | H7: =SUMIF('Семантическое ядро'!G:G,F7,'Семантическое ядро'!B:B) -> 1006 | I7: =H7/SUM('Семантическое ядро'!B:B) -> 0.0043640874
A8: Виниловая декоративная плёнка | B8: =COUNTIF('Семантическое ядро'!C:C,A8) -> 12 | C8: =SUMIF('Семантическое ядро'!C:C,A8,'Семантическое ядро'!B:B) -> 2090 | D8: =C8/SUM('Семантическое ядро'!B:B) -> 0.0090665433 | F8: Весь кузов | G8: =COUNTIF('Семантическое ядро'!G:G,F8) -> 9 | H8: =SUMIF('Семантическое ядро'!G:G,F8,'Семантическое ядро'!B:B) -> 1032 | I8: =H8/SUM('Семантическое ядро'!B:B) -> 0.0044768769
A9: PPF защитная плёнка | B9: =COUNTIF('Семантическое ядро'!C:C,A9) -> 2 | C9: =SUMIF('Семантическое ядро'!C:C,A9,'Семантическое ядро'!B:B) -> 1009 | D9: =C9/SUM('Семантическое ядро'!B:B) -> 0.0043771015 | F9: Бампер | G9: =COUNTIF('Семантическое ядро'!G:G,F9) -> 5 | H9: =SUMIF('Семантическое ядро'!G:G,F9,'Семантическое ядро'!B:B) -> 556 | I9: =H9/SUM('Семантическое ядро'!B:B) -> 0.0024119608
A10: Сравнение плёнка / керамика | B10: =COUNTIF('Семантическое ядро'!C:C,A10) -> 2 | C10: =SUMIF('Семантическое ядро'!C:C,A10,'Семантическое ядро'!B:B) -> 298 | D10: =C10/SUM('Семантическое ядро'!B:B) -> 0.0012927416 | F10: Зоны риска | G10: =COUNTIF('Семантическое ядро'!G:G,F10) -> 4 | H10: =SUMIF('Семантическое ядро'!G:G,F10,'Семантическое ядро'!B:B) -> 375 | I10: =H10/SUM('Семантическое ядро'!B:B) -> 0.0016267721
F11: Крылья | G11: =COUNTIF('Семантическое ядро'!G:G,F11) -> 1 | H11: =SUMIF('Семантическое ядро'!G:G,F11,'Семантическое ядро'!B:B) -> 109 | I11: =H11/SUM('Семантическое ядро'!B:B) -> 0.00047284843

Sheet Сводная таблица

Sheet Sheet1
A1: Формулировка | B1: Число запросов | C1: Кластер | D1: Релевантность | E1: Статус запроса (температура) | F1: Приоритет | G1: Элемент | H1: Релевантность (новая) | I1: Элемент (новый) | J1: Тип услуги | K1: Кластер (идеальный)
A2: оклейка пленкой | B2: 21001 | C2: Оклейка плёнкой — Общий / не указан | D2: Средняя | E2: Тёплый (коммерческий, выбирает исполнителя) | F2: Высокий | G2: Общий / не указан | H2: Средняя | I2: Общий / не указан | J2: Оклейка плёнкой | K2: Оклейка плёнкой — Общий / не указан
A3: оклейка авто | B3: 13852 | C3: Оклейка плёнкой — Общий / не указан | D3: Средняя | E3: Горячий (коммерческий) | F3: Высокий | G3: Общий / не указан | H3: Низкая | I3: Общий / не указан | J3: Оклейка плёнкой | K3: Оклейка плёнкой — Общий / не указан
A4: пленка цена | B4: 11460 | C4: Плёнка (общий запрос) — Общий / не указан | D4: Средняя | E4: Горячий (коммерческий) | F4: Высокий | G4: Общий / не указан | H4: Средняя | I4: Общий / не указан | J4: Плёнка (общий запрос) | K4: Плёнка (общий запрос) — Общий / не указан
A5: оклейка авто пленкой | B5: 8682 | C5: Оклейка плёнкой — Общий / не указан | D5: Высокая | E5: Тёплый (коммерческий, выбирает исполнителя) | F5: Высокий | G5: Общий / не указан | H5: Высокая | I5: Общий / не указан | J5: Оклейка плёнкой | K5: Оклейка плёнкой — Общий / не указан
A6: пленка на авто | B6: 5295 | C6: Плёнка (общий запрос) — Общий / не указан | D6: Высокая | E6: Средний интерес (изучает тему) | F6: Высокий | G6: Общий / не указан | H6: Высокая | I6: Общий / не указан | J6: Плёнка (общий запрос) | K6: Плёнка (общий запрос) — Общий / не указан
A7: цена оклейки | B7: 4050 | C7: Оклейка плёнкой — Общий / не указан | D7: Средняя | E7: Тёплый (коммерческий, выбирает исполнителя) | F7: Средний | G7: Общий / не указан | H7: Низкая | I7: Общий / не указан | J7: Оклейка плёнкой | K7: Оклейка плёнкой — Общий / не указан
A8: пленка на автомобиль | B8: 3947 | C8: Плёнка (общий запрос) — Общий / не указан | D8: Высокая | E8: Средний интерес (изучает тему) | F8: Высокий | G8: Общий / не указан | H8: Высокая | I8: Общий / не указан | J8: Плёнка (общий запрос) | K8: Плёнка (общий запрос) — Общий / не указан
A9: оклейка автомобиля | B9: 3526 | C9: Оклейка плёнкой — Общий / не указан | D9: Средняя | E9: Тёплый (коммерческий, выбирает исполнителя) | F9: Высокий | G9: Общий / не указан | H9: Низкая | I9: Общий / не указан | J9: Оклейка плёнкой | K9: Оклейка плёнкой — Общий / не указан
A10: оклейка пленкой москва | B10: 3001 | C10: Оклейка плёнкой — Общий / не указан | D10: Средняя | E10: Тёплый (коммерческий, выбирает исполнителя) | F10: Высокий | G10: Общий / не указан | H10: Средняя | I10: Общий / не указан | J10: Оклейка плёнкой | K10: Оклейка плёнкой — Общий / не указан
A11: оклейка машины | B11: 2915 | C11: Оклейка плёнкой — Общий / не указан | D11: Средняя | E11: Тёплый (коммерческий, выбирает исполнителя) | F11: Высокий | G11: Общий / не указан | H11: Низкая | I11: Общий / не указан | J11: Оклейка плёнкой | K11: Оклейка плёнкой — Общий / не указан
A12: оклейка пленкой цена | B12: 2772 | C12: Оклейка плёнкой — Общий / не указан | D12: Высокая | E12: Горячий (коммерческий) | F12: Высокий | G12: Общий / не указан | H12: Средняя | I12: Общий / не указан | J12: Оклейка плёнкой | K12: Оклейка плёнкой — Общий / не указан
A13: оклейка авто москва | B13: 2589 | C13: Оклейка плёнкой — Общий / не указан | D13: Средняя | E13: Тёплый (коммерческий, выбирает исполнителя) | F13: Высокий | G13: Общий / не указан | H13: Низкая | I13: Общий / не указан | J13: Оклейка плёнкой | K13: Оклейка плёнкой — Общий / не указан
... A692: полиуретановая пленка для фар автомобиля | B692: 50 | C692: Полиуретановая защитная плёнка — Фары | D692: Высокая | E692: Средний интерес (изучает тему) | F692: Низкий | G692: Фары | H692: Высокая | I692: Фары | J692: Полиуретановая пленка | K692: Полиуретановая пленка — Фары
